package/102103281.py
package/__init__.py
topsis_ishaan_102103281-1.0.dist-info/LICENSE
topsis_ishaan_102103281-1.0.dist-info/METADATA
topsis_ishaan_102103281-1.0.dist-info/WHEEL
topsis_ishaan_102103281-1.0.dist-info/entry_points.txt
topsis_ishaan_102103281-1.0.dist-info/top_level.txt
topsis_ishaan_102103281-1.0.dist-info/RECORD
