Metadata-Version: 2.1
Name: topsis-ishaan-102103281
Version: 1.0
Summary: TOPSIS
Author: Ishaan Gaba
Author-email: igaba_be21@thapar.edu
License: MIT
Keywords: TOPSIS,MCDM
Classifier: Development Status :: 4 - Beta
Classifier: Intended Audience :: Developers
Classifier: Topic :: Software Development :: Build Tools
Classifier: License :: OSI Approved :: MIT License
Classifier: Programming Language :: Python :: 3
License-File: LICENSE
Requires-Dist: numpy
Requires-Dist: pandas
